README.md
setup.cfg
setup.py
cashaddress/__init__.py
cashaddress/base58.py
cashaddress/convert.py
cashaddress/crypto.py
cashaddress.egg-info/PKG-INFO
cashaddress.egg-info/SOURCES.txt
cashaddress.egg-info/dependency_links.txt
cashaddress.egg-info/top_level.txt
tests/__init__.py
tests/test.py